hh.py
hh-2.0.0.dist-info/DESCRIPTION.rst
hh-2.0.0.dist-info/METADATA
hh-2.0.0.dist-info/RECORD
hh-2.0.0.dist-info/WHEEL
hh-2.0.0.dist-info/metadata.json
hh-2.0.0.dist-info/top_level.txt
hh-2.0.0.dist-info/zip-safe
