Metadata-Version: 2.0
Name: hh
Version: 2.0.0
Summary: The enumeration of HTTP headers.
Home-page: https://github.com/gtors/hh
Author: Andrey Torsunov
Author-email: andrey.torsunov@gmail.com
License: MIT
Platform: any
Classifier: Topic :: Internet
Classifier: Development Status :: 5 - Production/Stable
Classifier: License :: OSI Approved :: MIT License
Classifier: Environment :: Web Environment
Classifier: Programming Language :: Python :: 2
Classifier: Programming Language :: Python :: 3
